yoas_api_wrapper/__init__.py
yoas_api_wrapper/api_versions/__init__.py
yoas_api_wrapper/api_versions/v1/__init__.py
yoas_api_wrapper/api_versions/v1/dataclasses.py
yoas_api_wrapper/api_versions/v1/wrapper.py
yoas_api_wrapper-1.0.0.dist-info/LICENSE.txt
yoas_api_wrapper-1.0.0.dist-info/METADATA
yoas_api_wrapper-1.0.0.dist-info/WHEEL
yoas_api_wrapper-1.0.0.dist-info/top_level.txt
yoas_api_wrapper-1.0.0.dist-info/RECORD
