Metadata-Version: 2.2
Name: yoas_api_wrapper
Version: 1.0.0
Summary: Python wrapper for the YOAS (Your Own Anti-Spam System) API
Author-email: Pashok11 <pasha.m220@gmail.com>
License: MIT License
Project-URL: Homepage, https://github.com/Pashok111/YOAS-API-Wrapper
Project-URL: Repository, https://github.com/Pashok111/YOAS-API-Wrapper.git
Project-URL: Issues, https://github.com/Pashok111/YOAS-API-Wrapper/issues
Keywords: your own anti spam system,yoas,api,wrapper,pashok11
Classifier: Programming Language :: Python :: 3
Classifier: Operating System :: OS Independent
Requires-Python: >=3.8
License-File: LICENSE.txt
Requires-Dist: requests
